{
  "FormatType": 2,
  "DeckId": 8503332541,
  "Name": "无畏海盗",
  "HeroCardId": "HERO_10",
  "CardIds": [
    "JAM_017",
    "JAM_017",
    "TOY_518",
    "TOY_518",
    "VAC_512",
    "VAC_512",
    "MIS_710",
    "MIS_710",
    "DEEP_011",
    "DEEP_011",
    "VAC_419",
    "VAC_419",
    "VAC_933",
    "VAC_925",
    "VAC_925",
    "VAC_532",
    "VAC_532",
    "VAC_927",
    "VAC_927",
    "DEEP_014",
    "DEEP_014",
    "VAC_938",
    "VAC_938",
    "VAC_928",
    "VAC_928",
    "CORE_BT_187",
    "VAC_929",
    "VAC_929",
    "VAC_501",
    "TOY_330"
  ]
}